artefacts_toolkit/__init__.py
artefacts_toolkit/version.py
artefacts_toolkit/chart/__init__.py
artefacts_toolkit/config/__init__.py
artefacts_toolkit/gazebo/__init__.py
artefacts_toolkit/rosbag/__init__.py
artefacts_toolkit-1.0.0.dist-info/METADATA
artefacts_toolkit-1.0.0.dist-info/WHEEL
artefacts_toolkit-1.0.0.dist-info/top_level.txt
artefacts_toolkit-1.0.0.dist-info/RECORD
