Metadata-Version: 2.4
Name: artefacts_toolkit
Version: 1.0.0
Author-email: FD <fabian@artefacts.com>, AGC <alejandro@artefacts.com>, TN <tomo@artefacts.com>, EP <eric@artefacts.com>, BN <bach@artefacts.com>
Project-URL: Homepage, https://github.com/art-e-fact/artefacts-toolkit
Project-URL: Bug Tracker, https://github.com/art-e-fact/artefacts-toolkit
Classifier: Programming Language :: Python :: 3
Classifier: License :: OSI Approved :: Apache Software License
Classifier: Operating System :: OS Independent
Requires-Python: >=3.10
Requires-Dist: artefacts-toolkit-rosbag<0.5.0,>=0.4.0
Requires-Dist: artefacts-toolkit-config<0.3.0,>=0.2.3
Requires-Dist: artefacts-toolkit-gazebo<0.3.0,>=0.2.1
Requires-Dist: artefacts-toolkit-chart<1.1.0,>=1.0.0
Provides-Extra: dev
Requires-Dist: build; extra == "dev"
Requires-Dist: pyre-check; extra == "dev"
Requires-Dist: pytest; extra == "dev"
Requires-Dist: pytest-cov; extra == "dev"
Requires-Dist: pytest-env; extra == "dev"
Requires-Dist: pytest-mock; extra == "dev"
Requires-Dist: ruff; extra == "dev"
Requires-Dist: setuptools-scm; extra == "dev"
Requires-Dist: twine; extra == "dev"
